tweakers/__init__.py
tweakers/article.py
tweakers/comment.py
tweakers/exceptions.py
tweakers/frontpage.py
tweakers/gathering.py
tweakers/parsers.py
tweakers/topic.py
tweakers/user.py
tweakers/utils.py
tweakers-0.4.0.dist-info/LICENSE
tweakers-0.4.0.dist-info/METADATA
tweakers-0.4.0.dist-info/WHEEL
tweakers-0.4.0.dist-info/RECORD
