Metadata-Version: 2.1
Name: tweakers
Version: 0.4.0
Summary: A Python wrapper for tweakers.net
Home-page: https://github.com/timotk/tweakers
License: MIT
Author: Timo
Requires-Python: >=3.7,<3.12
Classifier: License :: OSI Approved :: MIT License
Classifier: Operating System :: OS Independent
Classifier: Programming Language :: Python :: 3
Classifier: Programming Language :: Python :: 3.7
Classifier: Programming Language :: Python :: 3.8
Classifier: Programming Language :: Python :: 3.9
Classifier: Programming Language :: Python :: 3.10
Classifier: Programming Language :: Python :: 3.11
Requires-Dist: dateparser (==1.1.8)
Requires-Dist: pydantic (>=2.1.1,<3.0.0)
Requires-Dist: requests-html (>=0.10.0,<0.11.0)
Requires-Dist: tenacity (>=6.2.0,<7.0.0)
Project-URL: Repository, https://github.com/timotk/tweakers
